<?xml version="1.0" encoding="UTF-8"?>
<activity acttype="dragdrop_multiple">
	<title oae-label="Title">
		<![CDATA[Drag and Drop Multi]]>
	</title>
	<instructions oae-label="Instructions" oae-type="textarea" oae-rows="3">
		<![CDATA[First listen to the conversation about salon services. Then complete each sentence. Drag the correct word(s) into each sentence.]]>
	</instructions>
	<spacer oae-type="spacer">
</spacer>

	<!-- Enter the text using <blank word="the word"/> syntax for the blank words/phrases. Enter optional distracters. -->


	<!-- There can be up to 3 blanks/distracters, e.g. one blank, one distracter, two blanks and one distracter, one blank two distracters, three blanks and no distracters, etc. -->

	<question>
		<audio oae-label="audio file name (optional). Please include the file extension (.mp3)" oae-type="textarea" oae-rows="1">
			<![CDATA[tn2e_lc_02_u05_c.mp3]]>
		</audio>
		<text>
			<![CDATA[The client wants to charge <blank word="a haircut "/> to her room.]]>
		</text>
		<distracter1>
			<![CDATA[a facial]]>
		</distracter1>
		<distracter2>
			<![CDATA[]]>
		</distracter2>
	</question>
	<question>
		<audio oae-label="audio file name (optional). Please include the file extension (.mp3)" oae-type="textarea" oae-rows="1">
			<![CDATA[tn2e_lc_02_u05_c.mp3]]>
		</audio>
		<text>
			<![CDATA[The salon is <blank word="in"/> a hotel.]]>
		</text>
		<distracter1>
			<![CDATA[not in]]>
		</distracter1>
		<distracter2>
			<![CDATA[]]>
		</distracter2>
	</question>
	<question>
		<audio oae-label="audio file name (optional). Please include the file extension (.mp3)" oae-type="textarea" oae-rows="1">
			<![CDATA[]]>
		</audio>
		<text>
			<![CDATA[The client is going to pay with <blank word="a credit card "/>.]]>
		</text>
		<distracter1>
			<![CDATA[cash]]>
		</distracter1>
		<distracter2>
			<![CDATA[]]>
		</distracter2>
	</question>
	<question>
		<audio oae-label="audio file name (optional). Please include the file extension (.mp3)" oae-type="textarea" oae-rows="1">
			<![CDATA[]]>
		</audio>
		<text>
			<![CDATA[]]>
		</text>
		<distracter1>
			<![CDATA[]]>
		</distracter1>
		<distracter2>
			<![CDATA[]]>
		</distracter2>
	</question>
	<question>
		<audio oae-label="audio file name (optional). Please include the file extension (.mp3)" oae-type="textarea" oae-rows="1">
			<![CDATA[]]>
		</audio>
		<text>
			<![CDATA[]]>
		</text>
		<distracter1>
			<![CDATA[]]>
		</distracter1>
		<distracter2>
			<![CDATA[]]>
		</distracter2>
	</question>
	<question>
		<audio oae-label="audio file name (optional). Please include the file extension (.mp3)" oae-type="textarea" oae-rows="1">
			<![CDATA[]]>
		</audio>
		<text>
			<![CDATA[]]>
		</text>
		<distracter1>
			<![CDATA[]]>
		</distracter1>
		<distracter2>
			<![CDATA[]]>
		</distracter2>
	</question>
	<question>
		<audio oae-label="audio file name (optional). Please include the file extension (.mp3)" oae-type="textarea" oae-rows="1">
			<![CDATA[]]>
		</audio>
		<text>
			<![CDATA[]]>
		</text>
		<distracter1>
			<![CDATA[]]>
		</distracter1>
		<distracter2>
			<![CDATA[]]>
		</distracter2>
	</question>
	<question>
		<audio oae-label="audio file name (optional). Please include the file extension (.mp3)" oae-type="textarea" oae-rows="1">
			<![CDATA[]]>
		</audio>
		<text>
			<![CDATA[]]>
		</text>
		<distracter1>
			<![CDATA[]]>
		</distracter1>
		<distracter2>
			<![CDATA[]]>
		</distracter2>
	</question>
	<question>
		<audio oae-label="audio file name (optional). Please include the file extension (.mp3)" oae-type="textarea" oae-rows="1">
			<![CDATA[]]>
		</audio>
		<text>
			<![CDATA[]]>
		</text>
		<distracter1>
			<![CDATA[]]>
		</distracter1>
		<distracter2>
			<![CDATA[]]>
		</distracter2>
	</question>
	<question>
		<audio oae-label="audio file name (optional). Please include the file extension (.mp3)" oae-type="textarea" oae-rows="1">
			<![CDATA[]]>
		</audio>
		<text>
			<![CDATA[]]>
		</text>
		<distracter1>
			<![CDATA[]]>
		</distracter1>
		<distracter2>
			<![CDATA[]]>
		</distracter2>
	</question>
</activity>
