<?xml version="1.0" encoding="UTF-8"?>
<activity acttype="multiple_choice" version="1.0" client="Longman" oae-label="ACTIVITY TYPE: Multiple Choice">
	<title oae-label="Activity Title" oae-type="textarea" oae-rows="1">
		<![CDATA[Multiple choice]]>
	</title>
	<instructions oae-label="Instructions" oae-type="textarea" oae-rows="3">
		<![CDATA[Click on the correct response.]]>
	</instructions>
	<questions>
		<question oae-label="Question 1">
			<graphic oae-label="graphic file name (optional). Please include the file extension (.jpg or .png)" oae-type="textarea" oae-rows="1">
				<![CDATA[]]>
			</graphic>
			<audio oae-label="audio file name (optional). Please include the file extension (.mp3)" oae-type="textarea" oae-rows="1">
				<![CDATA[]]>
			</audio>
			<reader oae-label="Reading text (optional)." oae-type="textarea" oae-rows="10">
				<![CDATA[]]>
			</reader>
			<text oae-label="Question Text" oae-type="textarea" oae-rows="3">
				<![CDATA[Am I interrupting you?]]>
			</text>
			<correct oae-label="Correct Answer" oae-type="textarea" oae-rows="2">
				<![CDATA[Not at all.]]>
			</correct>
			<distracters oae-label="Distracters">
				<distracter oae-label="Incorrect Answer 1" oae-type="textarea" oae-rows="2">
					<![CDATA[It couldn't hurt.]]>
				</distracter>
				<distracter oae-label="Incorrect Answer 2" oae-type="textarea" oae-rows="2">
					<![CDATA[What are you doing at this hour?]]>
				</distracter>
				<distracter oae-label="Incorrect Answer 3" oae-type="textarea" oae-rows="2">
					<![CDATA[That takes care of it.]]>
				</distracter>
				<distracter oae-label="Incorrect Answer 4" oae-type="textarea" oae-rows="2">
					<![CDATA[]]>
				</distracter>
			</distracters>
		</question>
		<question oae-label="Question 2">
			<graphic oae-label="graphic file name (optional). Please include the file extension (.jpg or .png)" oae-type="textarea" oae-rows="1">
				<![CDATA[]]>
			</graphic>
			<audio oae-label="audio file name (optional). Please include the file extension (.mp3)" oae-type="textarea" oae-rows="1">
				<![CDATA[]]>
			</audio>
			<reader oae-label="Reading text (optional)." oae-type="textarea" oae-rows="10">
				<![CDATA[]]>
			</reader>
			<text oae-label="Question Text" oae-type="textarea" oae-rows="3">
				<![CDATA[Could you help me with something?]]>
			</text>
			<correct oae-label="Correct Answer" oae-type="textarea" oae-rows="2">
				<![CDATA[Of course. What's the problem?]]>
			</correct>
			<distracters oae-label="Distracters">
				<distracter oae-label="Incorrect Answer 1" oae-type="textarea" oae-rows="2">
					<![CDATA[Not at all.]]>
				</distracter>
				<distracter oae-label="Incorrect Answer 2" oae-type="textarea" oae-rows="2">
					<![CDATA[I try to log on, but nothing happens.]]>
				</distracter>
				<distracter oae-label="Incorrect Answer 3" oae-type="textarea" oae-rows="2">
					<![CDATA[That sometimes works.]]>
				</distracter>
				<distracter oae-label="Incorrect Answer 4" oae-type="textarea" oae-rows="2">
					<![CDATA[]]>
				</distracter>
			</distracters>
		</question>
		<question oae-label="Question 3">
			<graphic oae-label="graphic file name (optional). Please include the file extension (.jpg or .png)" oae-type="textarea" oae-rows="1">
				<![CDATA[]]>
			</graphic>
			<audio oae-label="audio file name (optional). Please include the file extension (.mp3)" oae-type="textarea" oae-rows="1">
				<![CDATA[]]>
			</audio>
			<reader oae-label="Reading text (optional)." oae-type="textarea" oae-rows="10">
				<![CDATA[]]>
			</reader>
			<text oae-label="Question Text" oae-type="textarea" oae-rows="3">
				<![CDATA[My computer crashed.]]>
			</text>
			<correct oae-label="Correct Answer" oae-type="textarea" oae-rows="2">
				<![CDATA[Why don’t you try restarting?]]>
			</correct>
			<distracters oae-label="Distracters">
				<distracter oae-label="Incorrect Answer 1" oae-type="textarea" oae-rows="2">
					<![CDATA[Why don’t you cut and paste?]]>
				</distracter>
				<distracter oae-label="Incorrect Answer 2" oae-type="textarea" oae-rows="2">
					<![CDATA[Why don’t you click on the save icon?]]>
				</distracter>
				<distracter oae-label="Incorrect Answer 3" oae-type="textarea" oae-rows="2">
					<![CDATA[Why don’t you print it first?]]>
				</distracter>
				<distracter oae-label="Incorrect Answer 4" oae-type="textarea" oae-rows="2">
					<![CDATA[]]>
				</distracter>
			</distracters>
		</question>
		<question oae-label="Question 4">
			<graphic oae-label="graphic file name (optional). Please include the file extension (.jpg or .png)" oae-type="textarea" oae-rows="1">
				<![CDATA[]]>
			</graphic>
			<audio oae-label="audio file name (optional). Please include the file extension (.mp3)" oae-type="textarea" oae-rows="1">
				<![CDATA[]]>
			</audio>
			<reader oae-label="Reading text (optional)." oae-type="textarea" oae-rows="10">
				<![CDATA[]]>
			</reader>
			<text oae-label="Question Text" oae-type="textarea" oae-rows="3">
				<![CDATA[Everyone says I should get a new KONY TV.]]>
			</text>
			<correct oae-label="Correct Answer" oae-type="textarea" oae-rows="2">
				<![CDATA[Well, I’ve heard that the ZAX is just as good.]]>
			</correct>
			<distracters oae-label="Distracters">
				<distracter oae-label="Incorrect Answer 1" oae-type="textarea" oae-rows="2">
					<![CDATA[Really?  What kind?]]>
				</distracter>
				<distracter oae-label="Incorrect Answer 2" oae-type="textarea" oae-rows="2">
					<![CDATA[What are you up to?]]>
				</distracter>
				<distracter oae-label="Incorrect Answer 3" oae-type="textarea" oae-rows="2">
					<![CDATA[Just fooling around.]]>
				</distracter>
				<distracter oae-label="Incorrect Answer 4" oae-type="textarea" oae-rows="2">
					<![CDATA[]]>
				</distracter>
			</distracters>
		</question>
		<question oae-label="Question 5">
			<graphic oae-label="graphic file name (optional). Please include the file extension (.jpg or .png)" oae-type="textarea" oae-rows="1">
				<![CDATA[]]>
			</graphic>
			<audio oae-label="audio file name (optional). Please include the file extension (.mp3)" oae-type="textarea" oae-rows="1">
				<![CDATA[]]>
			</audio>
			<reader oae-label="Reading text (optional)." oae-type="textarea" oae-rows="10">
				<![CDATA[]]>
			</reader>
			<text oae-label="Question Text" oae-type="textarea" oae-rows="3">
				<![CDATA[Maybe you should try rebooting.]]>
			</text>
			<correct oae-label="Correct Answer" oae-type="textarea" oae-rows="2">
				<![CDATA[OK. I'll give that a try.]]>
			</correct>
			<distracters oae-label="Distracters">
				<distracter oae-label="Incorrect Answer 1" oae-type="textarea" oae-rows="2">
					<![CDATA[What's the problem?]]>
				</distracter>
				<distracter oae-label="Incorrect Answer 2" oae-type="textarea" oae-rows="2">
					<![CDATA[Could you take a look at this?]]>
				</distracter>
				<distracter oae-label="Incorrect Answer 3" oae-type="textarea" oae-rows="2">
					<![CDATA[Really? I'll check it out.]]>
				</distracter>
				<distracter oae-label="Incorrect Answer 4" oae-type="textarea" oae-rows="2">
					<![CDATA[]]>
				</distracter>
			</distracters>
		</question>
		<question oae-label="Question 6">
			<graphic oae-label="graphic file name (optional). Please include the file extension (.jpg or .png)" oae-type="textarea" oae-rows="1">
				<![CDATA[]]>
			</graphic>
			<audio oae-label="audio file name (optional). Please include the file extension (.mp3)" oae-type="textarea" oae-rows="1">
				<![CDATA[]]>
			</audio>
			<reader oae-label="Reading text (optional)." oae-type="textarea" oae-rows="10">
				<![CDATA[]]>
			</reader>
			<text oae-label="Question Text" oae-type="textarea" oae-rows="3">
				<![CDATA[]]>
			</text>
			<correct oae-label="Correct Answer" oae-type="textarea" oae-rows="2">
				<![CDATA[]]>
			</correct>
			<distracters oae-label="Distracters">
				<distracter oae-label="Incorrect Answer 1" oae-type="textarea" oae-rows="2">
					<![CDATA[]]>
				</distracter>
				<distracter oae-label="Incorrect Answer 2" oae-type="textarea" oae-rows="2">
					<![CDATA[]]>
				</distracter>
				<distracter oae-label="Incorrect Answer 3" oae-type="textarea" oae-rows="2">
					<![CDATA[]]>
				</distracter>
				<distracter oae-label="Incorrect Answer 4" oae-type="textarea" oae-rows="2">
					<![CDATA[]]>
				</distracter>
			</distracters>
		</question>
		<question oae-label="Question 7">
			<graphic oae-label="graphic file name (optional). Please include the file extension (.jpg or .png)" oae-type="textarea" oae-rows="1">
				<![CDATA[]]>
			</graphic>
			<audio oae-label="audio file name (optional). Please include the file extension (.mp3)" oae-type="textarea" oae-rows="1">
				<![CDATA[]]>
			</audio>
			<reader oae-label="Reading text (optional)." oae-type="textarea" oae-rows="10">
				<![CDATA[]]>
			</reader>
			<text oae-label="Question Text" oae-type="textarea" oae-rows="3">
				<![CDATA[]]>
			</text>
			<correct oae-label="Correct Answer" oae-type="textarea" oae-rows="2">
				<![CDATA[]]>
			</correct>
			<distracters oae-label="Distracters">
				<distracter oae-label="Incorrect Answer 1" oae-type="textarea" oae-rows="2">
					<![CDATA[]]>
				</distracter>
				<distracter oae-label="Incorrect Answer 2" oae-type="textarea" oae-rows="2">
					<![CDATA[]]>
				</distracter>
				<distracter oae-label="Incorrect Answer 3" oae-type="textarea" oae-rows="2">
					<![CDATA[]]>
				</distracter>
				<distracter oae-label="Incorrect Answer 4" oae-type="textarea" oae-rows="2">
					<![CDATA[]]>
				</distracter>
			</distracters>
		</question>
		<question oae-label="Question 8">
			<graphic oae-label="graphic file name (optional). Please include the file extension (.jpg or .png)" oae-type="textarea" oae-rows="1">
				<![CDATA[]]>
			</graphic>
			<audio oae-label="audio file name (optional). Please include the file extension (.mp3)" oae-type="textarea" oae-rows="1">
				<![CDATA[]]>
			</audio>
			<reader oae-label="Reading text (optional)." oae-type="textarea" oae-rows="10">
				<![CDATA[]]>
			</reader>
			<text oae-label="Question Text" oae-type="textarea" oae-rows="3">
				<![CDATA[]]>
			</text>
			<correct oae-label="Correct Answer" oae-type="textarea" oae-rows="2">
				<![CDATA[]]>
			</correct>
			<distracters oae-label="Distracters">
				<distracter oae-label="Incorrect Answer 1" oae-type="textarea" oae-rows="2">
					<![CDATA[]]>
				</distracter>
				<distracter oae-label="Incorrect Answer 2" oae-type="textarea" oae-rows="2">
					<![CDATA[]]>
				</distracter>
				<distracter oae-label="Incorrect Answer 3" oae-type="textarea" oae-rows="2">
					<![CDATA[]]>
				</distracter>
				<distracter oae-label="Incorrect Answer 4" oae-type="textarea" oae-rows="2">
					<![CDATA[]]>
				</distracter>
			</distracters>
		</question>
		<question oae-label="Question 9">
			<graphic oae-label="graphic file name (optional). Please include the file extension (.jpg or .png)" oae-type="textarea" oae-rows="1">
				<![CDATA[]]>
			</graphic>
			<audio oae-label="audio file name (optional). Please include the file extension (.mp3)" oae-type="textarea" oae-rows="1">
				<![CDATA[]]>
			</audio>
			<reader oae-label="Reading text (optional)." oae-type="textarea" oae-rows="10">
				<![CDATA[]]>
			</reader>
			<text oae-label="Question Text" oae-type="textarea" oae-rows="3">
				<![CDATA[]]>
			</text>
			<correct oae-label="Correct Answer" oae-type="textarea" oae-rows="2">
				<![CDATA[]]>
			</correct>
			<distracters oae-label="Distracters">
				<distracter oae-label="Incorrect Answer 1" oae-type="textarea" oae-rows="2">
					<![CDATA[]]>
				</distracter>
				<distracter oae-label="Incorrect Answer 2" oae-type="textarea" oae-rows="2">
					<![CDATA[]]>
				</distracter>
				<distracter oae-label="Incorrect Answer 3" oae-type="textarea" oae-rows="2">
					<![CDATA[]]>
				</distracter>
				<distracter oae-label="Incorrect Answer 4" oae-type="textarea" oae-rows="2">
					<![CDATA[]]>
				</distracter>
			</distracters>
		</question>
		<question oae-label="Question 10">
			<graphic oae-label="graphic file name (optional). Please include the file extension (.jpg or .png)" oae-type="textarea" oae-rows="1">
				<![CDATA[]]>
			</graphic>
			<audio oae-label="audio file name (optional). Please include the file extension (.mp3)" oae-type="textarea" oae-rows="1">
				<![CDATA[]]>
			</audio>
			<reader oae-label="Reading text (optional)." oae-type="textarea" oae-rows="10">
				<![CDATA[]]>
			</reader>
			<text oae-label="Question Text" oae-type="textarea" oae-rows="3">
				<![CDATA[]]>
			</text>
			<correct oae-label="Correct Answer" oae-type="textarea" oae-rows="2">
				<![CDATA[]]>
			</correct>
			<distracters oae-label="Distracters">
				<distracter oae-label="Incorrect Answer 1" oae-type="textarea" oae-rows="2">
					<![CDATA[]]>
				</distracter>
				<distracter oae-label="Incorrect Answer 2" oae-type="textarea" oae-rows="2">
					<![CDATA[]]>
				</distracter>
				<distracter oae-label="Incorrect Answer 3" oae-type="textarea" oae-rows="2">
					<![CDATA[]]>
				</distracter>
				<distracter oae-label="Incorrect Answer 4" oae-type="textarea" oae-rows="2">
					<![CDATA[]]>
				</distracter>
			</distracters>
		</question>
	</questions>
</activity>
