<?xml version="1.0" encoding="UTF-8"?>
<activity acttype="concentration" version="1.0" client="Longman" oae-label="ACTIVITY TYPE: Concentration">
	<title oae-label="Activity Title" oae-type="textarea" oae-rows="1">
		<![CDATA[Concentration]]>
	</title>
	<instructions oae-label="Instructions" oae-type="textarea" oae-rows="3">
		<![CDATA[Click on the cards.  Match the pictures with the words you hear.]]>
	</instructions>
	<correctFlipDelay oae-label="Delay time (milliseconds) before a correct match is cleared" oae-type="textarea" oae-rows="1" value="1000">
		<![CDATA[750]]>
	</correctFlipDelay>
	<incorrectFlipDelay oae-label="Delay time (milliseconds) before an incorrect match is flipped over" oae-type="textarea" oae-rows="1" value="2000">
		<![CDATA[750]]>
	</incorrectFlipDelay>
	<matches>
		<match oae-label="Matching Set 1">
			<card_one oae-label="First Card">
				<text oae-label="Text" oae-type="textarea" oae-rows="2">
					<![CDATA[]]>
				</text>
				<graphic oae-label="Graphic file name (optional). Please include the file extension (.jpg or .png)" oae-type="textarea" oae-rows="1">
					<![CDATA[tn2_5_1.jpg]]>
				</graphic>
				<audio oae-label="Audio file name (optional). Please include the file extension (.mp3)" oae-type="textarea" oae-rows="1">
					<![CDATA[]]>
				</audio>
			</card_one>
			<card_two oae-label="Second Card">
				<text oae-label="Text" oae-type="textarea" oae-rows="2">
					<![CDATA[]]>
				</text>
				<graphic oae-label="Graphic file name (optional). Please include the file extension (.jpg or .png)" oae-type="textarea" oae-rows="1">
					<![CDATA[]]>
				</graphic>
				<audio oae-label="Audio file name (optional). Please include the file extension (.mp3)" oae-type="textarea" oae-rows="1">
					<![CDATA[tn2_5_1.mp3]]>
				</audio>
			</card_two>
		</match>
		<match oae-label="Matching Set 2">
			<card_one oae-label="First Card">
				<text oae-label="Text" oae-type="textarea" oae-rows="2">
					<![CDATA[]]>
				</text>
				<graphic oae-label="Graphic file name (optional). Please include the file extension (.jpg or .png)" oae-type="textarea" oae-rows="1">
					<![CDATA[tn2_5_3.jpg]]>
				</graphic>
				<audio oae-label="Audio file name (optional). Please include the file extension (.mp3)" oae-type="textarea" oae-rows="1">
					<![CDATA[]]>
				</audio>
			</card_one>
			<card_two oae-label="Second Card">
				<text oae-label="Text" oae-type="textarea" oae-rows="2">
					<![CDATA[]]>
				</text>
				<graphic oae-label="Graphic file name (optional). Please include the file extension (.jpg or .png)" oae-type="textarea" oae-rows="1">
					<![CDATA[]]>
				</graphic>
				<audio oae-label="Audio file name (optional). Please include the file extension (.mp3)" oae-type="textarea" oae-rows="1">
					<![CDATA[tn2_5_2.mp3]]>
				</audio>
			</card_two>
		</match>
		<match oae-label="Matching Set 3">
			<card_one oae-label="First Card">
				<text oae-label="Text" oae-type="textarea" oae-rows="2">
					<![CDATA[]]>
				</text>
				<graphic oae-label="Graphic file name (optional). Please include the file extension (.jpg or .png)" oae-type="textarea" oae-rows="1">
					<![CDATA[tn2_5_5.jpg]]>
				</graphic>
				<audio oae-label="Audio file name (optional). Please include the file extension (.mp3)" oae-type="textarea" oae-rows="1">
					<![CDATA[]]>
				</audio>
			</card_one>
			<card_two oae-label="Second Card">
				<text oae-label="Text" oae-type="textarea" oae-rows="2">
					<![CDATA[]]>
				</text>
				<graphic oae-label="Graphic file name (optional). Please include the file extension (.jpg or .png)" oae-type="textarea" oae-rows="1">
					<![CDATA[]]>
				</graphic>
				<audio oae-label="Audio file name (optional). Please include the file extension (.mp3)" oae-type="textarea" oae-rows="1">
					<![CDATA[tn2_5_3.mp3]]>
				</audio>
			</card_two>
		</match>
		<match oae-label="Matching Set 4">
			<card_one oae-label="First Card">
				<text oae-label="Text" oae-type="textarea" oae-rows="2">
					<![CDATA[]]>
				</text>
				<graphic oae-label="Graphic file name (optional). Please include the file extension (.jpg or .png)" oae-type="textarea" oae-rows="1">
					<![CDATA[tn2e_2_5_7.jpg]]>
				</graphic>
				<audio oae-label="Audio file name (optional). Please include the file extension (.mp3)" oae-type="textarea" oae-rows="1">
					<![CDATA[]]>
				</audio>
			</card_one>
			<card_two oae-label="Second Card">
				<text oae-label="Text" oae-type="textarea" oae-rows="2">
					<![CDATA[]]>
				</text>
				<graphic oae-label="Graphic file name (optional). Please include the file extension (.jpg or .png)" oae-type="textarea" oae-rows="1">
					<![CDATA[]]>
				</graphic>
				<audio oae-label="Audio file name (optional). Please include the file extension (.mp3)" oae-type="textarea" oae-rows="1">
					<![CDATA[tn2e_2_5_7.mp3]]>
				</audio>
			</card_two>
		</match>
		<match oae-label="Matching Set 5">
			<card_one oae-label="First Card">
				<text oae-label="Text" oae-type="textarea" oae-rows="2">
					<![CDATA[]]>
				</text>
				<graphic oae-label="Graphic file name (optional). Please include the file extension (.jpg or .png)" oae-type="textarea" oae-rows="1">
					<![CDATA[tn2_5_9.jpg]]>
				</graphic>
				<audio oae-label="Audio file name (optional). Please include the file extension (.mp3)" oae-type="textarea" oae-rows="1">
					<![CDATA[]]>
				</audio>
			</card_one>
			<card_two oae-label="Second Card">
				<text oae-label="Text" oae-type="textarea" oae-rows="2">
					<![CDATA[]]>
				</text>
				<graphic oae-label="Graphic file name (optional). Please include the file extension (.jpg or .png)" oae-type="textarea" oae-rows="1">
					<![CDATA[]]>
				</graphic>
				<audio oae-label="Audio file name (optional). Please include the file extension (.mp3)" oae-type="textarea" oae-rows="1">
					<![CDATA[tn2_5_5.mp3]]>
				</audio>
			</card_two>
		</match>
		<match oae-label="Matching Set 6">
			<card_one oae-label="First Card">
				<text oae-label="Text" oae-type="textarea" oae-rows="2">
					<![CDATA[]]>
				</text>
				<graphic oae-label="Graphic file name (optional). Please include the file extension (.jpg or .png)" oae-type="textarea" oae-rows="1">
					<![CDATA[tn2_5_11.jpg]]>
				</graphic>
				<audio oae-label="Audio file name (optional). Please include the file extension (.mp3)" oae-type="textarea" oae-rows="1">
					<![CDATA[]]>
				</audio>
			</card_one>
			<card_two oae-label="Second Card">
				<text oae-label="Text" oae-type="textarea" oae-rows="2">
					<![CDATA[]]>
				</text>
				<graphic oae-label="Graphic file name (optional). Please include the file extension (.jpg or .png)" oae-type="textarea" oae-rows="1">
					<![CDATA[]]>
				</graphic>
				<audio oae-label="Audio file name (optional). Please include the file extension (.mp3)" oae-type="textarea" oae-rows="1">
					<![CDATA[tn2_5_6.mp3]]>
				</audio>
			</card_two>
		</match>
		<match oae-label="Matching Set 7">
			<card_one oae-label="First Card">
				<text oae-label="Text" oae-type="textarea" oae-rows="2">
					<![CDATA[]]>
				</text>
				<graphic oae-label="Graphic file name (optional). Please include the file extension (.jpg or .png)" oae-type="textarea" oae-rows="1">
					<![CDATA[tn2e_2_5_13.jpg]]>
				</graphic>
				<audio oae-label="Audio file name (optional). Please include the file extension (.mp3)" oae-type="textarea" oae-rows="1">
					<![CDATA[]]>
				</audio>
			</card_one>
			<card_two oae-label="Second Card">
				<text oae-label="Text" oae-type="textarea" oae-rows="2">
					<![CDATA[]]>
				</text>
				<graphic oae-label="Graphic file name (optional). Please include the file extension (.jpg or .png)" oae-type="textarea" oae-rows="1">
					<![CDATA[]]>
				</graphic>
				<audio oae-label="Audio file name (optional). Please include the file extension (.mp3)" oae-type="textarea" oae-rows="1">
					<![CDATA[tn2e_2_5_13.mp3]]>
				</audio>
			</card_two>
		</match>
		<match oae-label="Matching Set 8">
			<card_one oae-label="First Card">
				<text oae-label="Text" oae-type="textarea" oae-rows="2">
					<![CDATA[]]>
				</text>
				<graphic oae-label="Graphic file name (optional). Please include the file extension (.jpg or .png)" oae-type="textarea" oae-rows="1">
					<![CDATA[tn2_5_15.jpg]]>
				</graphic>
				<audio oae-label="Audio file name (optional). Please include the file extension (.mp3)" oae-type="textarea" oae-rows="1">
					<![CDATA[]]>
				</audio>
			</card_one>
			<card_two oae-label="Second Card">
				<text oae-label="Text" oae-type="textarea" oae-rows="2">
					<![CDATA[]]>
				</text>
				<graphic oae-label="Graphic file name (optional). Please include the file extension (.jpg or .png)" oae-type="textarea" oae-rows="1">
					<![CDATA[]]>
				</graphic>
				<audio oae-label="Audio file name (optional). Please include the file extension (.mp3)" oae-type="textarea" oae-rows="1">
					<![CDATA[tn2_5_8.mp3]]>
				</audio>
			</card_two>
		</match>
	</matches>
</activity>
