<?xml version="1.0" encoding="UTF-8"?>
<activity acttype="word_scramble" version="1.0" client="Longman" oae-label="ACTIVITY TYPE: Scrambled Words">
	<title oae-label="Title">
		<![CDATA[Word Scramble]]>
	</title>
	<instructions oae-label="Instructions" oae-type="textarea" oae-rows="3">
		<![CDATA[Make a sentence.  Drag each word to the correct number.]]>
	</instructions>
	<spacer oae-type="spacer">
</spacer>
	<sentence oae-label="Sentence 1">
		<word>
			<![CDATA[That]]>
		</word>
		<word>
			<![CDATA[famous]]>
		</word>
		<word>
			<![CDATA[movie]]>
		</word>
		<word>
			<![CDATA[was]]>
		</word>
		<word>
			<![CDATA[filmed]]>
		</word>
		<word>
			<![CDATA[in]]>
		</word>
		<word>
			<![CDATA[1972.]]>
		</word>
		<word>
			<![CDATA[]]>
		</word>
		<word>
			<![CDATA[]]>
		</word>
		<word>
			<![CDATA[]]>
		</word>
		<word>
			<![CDATA[]]>
		</word>
		<word>
			<![CDATA[]]>
		</word>
	</sentence>
	<sentence oae-label="Sentence 2">
		<word>
			<![CDATA[His]]>
		</word>
		<word>
			<![CDATA[artwork]]>
		</word>
		<word>
			<![CDATA[is]]>
		</word>
		<word>
			<![CDATA[inspired]]>
		</word>
		<word>
			<![CDATA[by]]>
		</word>
		<word>
			<![CDATA[Picasso.]]>
		</word>
		<word>
			<![CDATA[]]>
		</word>
		<word>
			<![CDATA[]]>
		</word>
		<word>
			<![CDATA[]]>
		</word>
		<word>
			<![CDATA[]]>
		</word>
		<word>
			<![CDATA[]]>
		</word>
		<word>
			<![CDATA[]]>
		</word>
	</sentence>
	<sentence oae-label="Sentence 3">
		<word>
			<![CDATA[Were]]>
		</word>
		<word>
			<![CDATA[those]]>
		</word>
		<word>
			<![CDATA[wood]]>
		</word>
		<word>
			<![CDATA[sculptures]]>
		</word>
		<word>
			<![CDATA[made]]>
		</word>
		<word>
			<![CDATA[by]]>
		</word>
		<word>
			<![CDATA[hand?]]>
		</word>
		<word>
			<![CDATA[]]>
		</word>
		<word>
			<![CDATA[]]>
		</word>
		<word>
			<![CDATA[]]>
		</word>
		<word>
			<![CDATA[]]>
		</word>
		<word>
			<![CDATA[]]>
		</word>
	</sentence>
	<sentence oae-label="Sentence 4">
		<word>
			<![CDATA[Where]]>
		</word>
		<word>
			<![CDATA[is]]>
		</word>
		<word>
			<![CDATA[that]]>
		</word>
		<word>
			<![CDATA[painting]]>
		</word>
		<word>
			<![CDATA[kept?]]>
		</word>
		<word>
			<![CDATA[]]>
		</word>
		<word>
			<![CDATA[]]>
		</word>
		<word>
			<![CDATA[]]>
		</word>
		<word>
			<![CDATA[]]>
		</word>
		<word>
			<![CDATA[]]>
		</word>
		<word>
			<![CDATA[]]>
		</word>
		<word>
			<![CDATA[]]>
		</word>
	</sentence>
	<sentence oae-label="Sentence 5">
		<word>
			<![CDATA[Those]]>
		</word>
		<word>
			<![CDATA[cloth]]>
		</word>
		<word>
			<![CDATA[bags]]>
		</word>
		<word>
			<![CDATA[were]]>
		</word>
		<word>
			<![CDATA[made]]>
		</word>
		<word>
			<![CDATA[in]]>
		</word>
		<word>
			<![CDATA[Spain.]]>
		</word>
		<word>
			<![CDATA[]]>
		</word>
		<word>
			<![CDATA[]]>
		</word>
		<word>
			<![CDATA[]]>
		</word>
		<word>
			<![CDATA[]]>
		</word>
		<word>
			<![CDATA[]]>
		</word>
	</sentence>
	<sentence oae-label="Sentence 6">
		<word>
			<![CDATA[This]]>
		</word>
		<word>
			<![CDATA[vase]]>
		</word>
		<word>
			<![CDATA[was]]>
		</word>
		<word>
			<![CDATA[made]]>
		</word>
		<word>
			<![CDATA[in]]>
		</word>
		<word>
			<![CDATA[the]]>
		</word>
		<word>
			<![CDATA[seventh]]>
		</word>
		<word>
			<![CDATA[century.]]>
		</word>
		<word>
			<![CDATA[]]>
		</word>
		<word>
			<![CDATA[]]>
		</word>
		<word>
			<![CDATA[]]>
		</word>
		<word>
			<![CDATA[]]>
		</word>
	</sentence>
</activity>
